LICENSE
README.md
setup.py
llm_pricing/__init__.py
llm_pricing/anthropic.py
llm_pricing/api.py
llm_pricing/pricing_schemas.py
llm_pricing/py.typed
llm_pricing/scraper.py
llm_pricing.egg-info/PKG-INFO
llm_pricing.egg-info/SOURCES.txt
llm_pricing.egg-info/dependency_links.txt
llm_pricing.egg-info/requires.txt
llm_pricing.egg-info/top_level.txt