Metadata-Version: 2.4
Name: llm-pricing
Version: 0.1.3
Summary: A library for scraping and managing LLM pricing information
Home-page: https://github.com/fswair/llm-pricing
Author: fswair
Author-email: contact@tomris.dev
Project-URL: Bug Reports, https://github.com/fswair/llm-pricing/issues
Project-URL: Source, https://github.com/fswair/llm-pricing
Keywords: llm pricing,llm api,llm api cost
Classifier: Development Status :: 2 - Pre-Alpha
Classifier: Intended Audience :: Developers
Classifier: Topic :: Software Development :: Libraries :: Python Modules
Classifier: License :: OSI Approved :: MIT License
Classifier: Programming Language :: Python :: 3
Classifier: Programming Language :: Python :: 3.10
Classifier: Programming Language :: Python :: 3.11
Classifier: Programming Language :: Python :: 3.12
Classifier: Programming Language :: Python :: 3.13
Requires-Python: >=3.10
License-File: LICENSE
Requires-Dist: brotli
Requires-Dist: uvicorn
Requires-Dist: fastapi
Requires-Dist: aiohttp
Requires-Dist: aiocache
Requires-Dist: pydantic
Requires-Dist: user-agent
Requires-Dist: cache-fastapi
Requires-Dist: python-dotenv
Requires-Dist: beautifulsoup4
Requires-Dist: aiohttp[brotli]
Dynamic: author
Dynamic: author-email
Dynamic: classifier
Dynamic: description
Dynamic: description-content-type
Dynamic: home-page
Dynamic: keywords
Dynamic: license-file
Dynamic: project-url
Dynamic: requires-dist
Dynamic: requires-python
Dynamic: summary
